octomizer/__init__.py
octomizer/auth.py
octomizer/client.py
octomizer/examples/octomizer_example_account_admin.py
octomizer/logging_.py
octomizer/model.py
octomizer/model_inputs.py
octomizer/model_variant.py
octomizer/models/__init__.py
octomizer/models/onnx_model.py
octomizer/models/tensorflow_graph_def_model.py
octomizer/models/tensorflow_saved_model.py
octomizer/models/tflite_model.py
octomizer/models/torchscript_model.py
octomizer/package_type.py
octomizer/package_workflow_group.py
octomizer/project.py
octomizer/user.py
octomizer/workflow.py
octoml/__init__.py
octoml/octomizer/__init__.py
octoml/octomizer/v1/__init__.py
octoml/octomizer/v1/autotune_pb2.py
octoml/octomizer/v1/autotune_pb2_grpc.py
octoml/octomizer/v1/benchmark_pb2.py
octoml/octomizer/v1/benchmark_pb2_grpc.py
octoml/octomizer/v1/datarefs_pb2.py
octoml/octomizer/v1/datarefs_pb2_grpc.py
octoml/octomizer/v1/engine_pb2.py
octoml/octomizer/v1/engine_pb2_grpc.py
octoml/octomizer/v1/error_pb2.py
octoml/octomizer/v1/error_pb2_grpc.py
octoml/octomizer/v1/hardware_pb2.py
octoml/octomizer/v1/hardware_pb2_grpc.py
octoml/octomizer/v1/hardware_targets_pb2.py
octoml/octomizer/v1/hardware_targets_pb2_grpc.py
octoml/octomizer/v1/ingest_model_status_pb2.py
octoml/octomizer/v1/ingest_model_status_pb2_grpc.py
octoml/octomizer/v1/model_inputs_pb2.py
octoml/octomizer/v1/model_inputs_pb2_grpc.py
octoml/octomizer/v1/models_pb2.py
octoml/octomizer/v1/models_pb2_grpc.py
octoml/octomizer/v1/octomizer_service_pb2.py
octoml/octomizer/v1/octomizer_service_pb2_grpc.py
octoml/octomizer/v1/package_pb2.py
octoml/octomizer/v1/package_pb2_grpc.py
octoml/octomizer/v1/projects_pb2.py
octoml/octomizer/v1/projects_pb2_grpc.py
octoml/octomizer/v1/tokens_pb2.py
octoml/octomizer/v1/tokens_pb2_grpc.py
octoml/octomizer/v1/users_pb2.py
octoml/octomizer/v1/users_pb2_grpc.py
octoml/octomizer/v1/workflows_pb2.py
octoml/octomizer/v1/workflows_pb2_grpc.py
octoml/py.typed
octomizer_sdk-0.13.1.dist-info/entry_points.txt
octomizer_sdk-0.13.1.dist-info/LICENSE
octomizer_sdk-0.13.1.dist-info/WHEEL
octomizer_sdk-0.13.1.dist-info/METADATA
octomizer_sdk-0.13.1.dist-info/RECORD
