Metadata-Version: 2.1
Name: octomizer-sdk
Version: 0.13.1
Summary: Machine learning optimization and deployment using OctoML.
Home-page: https://octoml.ai/
License: Apache-2.0
Author: Matt Welsh
Author-email: mdw@octoml.ai
Requires-Python: >=3.7,<4.0
Classifier: License :: OSI Approved :: Apache Software License
Classifier: Programming Language :: Python :: 3
Classifier: Programming Language :: Python :: 3.7
Classifier: Programming Language :: Python :: 3.8
Classifier: Programming Language :: Python :: 3.9
Classifier: Programming Language :: Python :: 3.10
Requires-Dist: click (>=8.0.0,<9.0.0)
Requires-Dist: google-api-core (==1.22.2)
Requires-Dist: googleapis-common-protos (==1.56.4)
Requires-Dist: grpcio (==1.38.1)
Requires-Dist: grpcio-status (>=1.35.0,<2.0.0)
Requires-Dist: grpcio-tools (>=1.32.0,<2.0.0)
Requires-Dist: pyjwt (>=2.0.1,<3.0.0)
Requires-Dist: requests (>=2.23.0,<3.0.0)
Requires-Dist: sphinx-copybutton (>=0.5.0,<0.6.0)
Requires-Dist: sphinx-rtd-theme (>=0.5.2,<0.6.0)
